MacToManufacturer/__init__.py
MacToManufacturer/main.py
MacToManufacturer/data/manuf.csv
MacToManufacturer-0.2.0.dist-info/LICENSE.txt
MacToManufacturer-0.2.0.dist-info/METADATA
MacToManufacturer-0.2.0.dist-info/WHEEL
MacToManufacturer-0.2.0.dist-info/top_level.txt
MacToManufacturer-0.2.0.dist-info/RECORD
