Metadata-Version: 2.1
Name: MacToManufacturer
Version: 0.2.0
Summary: Library to find manufacturer of a device using macaddress.
Home-page: https://github.com/n1snt/MacToManufacturer
Author: Nishant Bhandari
Author-email: getrooted0019@hotmail.com
License: UNKNOWN
Project-URL: Bug Tracker, https://github.com/n1snt/MacToManufacturer/issues
Platform: UNKNOWN
Classifier: Programming Language :: Python :: 3
Classifier: License :: OSI Approved :: MIT License
Classifier: Operating System :: OS Independent
Requires-Python: >=3.6
License-File: LICENSE.txt
